<GDAL_WMS>
  <Service name="WMS">
    <Version>1.1.1</Version>
    <ServerUrl>http://planetarymaps.usgs.gov/cgi-bin/mapserv?map=/maps/mars/mars_simp_cyl.map</ServerUrl>
    <SRS>EPSG:4326</SRS>
    <ImageFormat>image/jpeg</ImageFormat>
    <Layers>MDIM21</Layers>
  </Service>
  <DataWindow>
    <UpperLeftX>280</UpperLeftX>
    <UpperLeftY>45</UpperLeftY>
    <LowerRightX>290</LowerRightX>
    <LowerRightY>35</LowerRightY>
     <SizeX>1000</SizeX>
     <SizeY>1000</SizeY>
  </DataWindow>
  <Projection>EPSG:4326</Projection>
  <BandsCount>3</BandsCount>
  <DataType>Byte</DataType>
</GDAL_WMS>
